social_edu_federation/__init__.py
social_edu_federation/defaults.py
social_edu_federation/metadata_store.py
social_edu_federation/parser.py
social_edu_federation/backends/__init__.py
social_edu_federation/backends/base.py
social_edu_federation/backends/saml_fer.py
social_edu_federation/django/__init__.py
social_edu_federation/django/apps.py
social_edu_federation/django/checks.py
social_edu_federation/django/metadata_store.py
social_edu_federation/django/views.py
social_edu_federation/django/management/commands/__init__.py
social_edu_federation/django/management/commands/prefetch_saml_fer_metadata.py
social_edu_federation/django/static/css/social_edu_federation/base.css
social_edu_federation/django/templates/social_edu_federation/available_idps_list.html
social_edu_federation/django/templates/social_edu_federation/base.html
social_edu_federation/django/templates/testing/fake_saml_idp_sso_login.html
social_edu_federation/django/testing/__init__.py
social_edu_federation/django/testing/forms.py
social_edu_federation/django/testing/urls.py
social_edu_federation/django/testing/views.py
social_edu_federation/pipeline/__init__.py
social_edu_federation/pipeline/user.py
social_edu_federation/testing/__init__.py
social_edu_federation/testing/certificates.py
social_edu_federation/testing/saml_tools.py
social_edu_federation/testing/settings.py
social_edu_federation-2.1.1.dist-info/LICENSE
social_edu_federation-2.1.1.dist-info/METADATA
social_edu_federation-2.1.1.dist-info/WHEEL
social_edu_federation-2.1.1.dist-info/top_level.txt
social_edu_federation-2.1.1.dist-info/zip-safe
social_edu_federation-2.1.1.dist-info/RECORD
