Metadata-Version: 2.1
Name: social-edu-federation
Version: 2.1.1
Summary: An SAML backend for python-social-auth dedicated to education federation (RENATER)
Home-page: https://github.com/openfun/social-edu-federation
Author: Open FUN (France Universite Numerique)
Author-email: fun.dev@fun-mooc.fr
License: MIT
Keywords: python3-saml,python-social-auth,renater,shibboleth,Federation Education-Recherche
Classifier: Development Status :: 5 - Production/Stable
Classifier: Intended Audience :: Education
Classifier: Intended Audience :: Developers
Classifier: License :: OSI Approved :: MIT License
Classifier: Programming Language :: Python
Classifier: Programming Language :: Python :: 3
Classifier: Programming Language :: Python :: 3.8
Classifier: Programming Language :: Python :: 3.9
Classifier: Programming Language :: Python :: 3.10
Classifier: Programming Language :: Python :: 3 :: Only
License-File: LICENSE
Requires-Dist: social-auth-app-django (>=5.0.0)
Requires-Dist: social-auth-core[saml] (>=4.2.0)
Provides-Extra: dev
Requires-Dist: bandit (==1.7.4) ; extra == 'dev'
Requires-Dist: black (==22.3.0) ; extra == 'dev'
Requires-Dist: check-manifest (==0.48) ; extra == 'dev'
Requires-Dist: cryptography (==37.0.2) ; extra == 'dev'
Requires-Dist: flake8 (==4.0.1) ; extra == 'dev'
Requires-Dist: httpretty (==1.1.4) ; extra == 'dev'
Requires-Dist: ipython (==8.4.0) ; extra == 'dev'
Requires-Dist: isort (==5.10.1) ; extra == 'dev'
Requires-Dist: pycodestyle (==2.8.0) ; extra == 'dev'
Requires-Dist: pylint (==2.13.9) ; extra == 'dev'
Requires-Dist: pylint-pytest (==1.1.2) ; extra == 'dev'
Requires-Dist: pyOpenSSL (==20.0.1) ; extra == 'dev'
Requires-Dist: pytest (==7.1.2) ; extra == 'dev'
Requires-Dist: pytest-cov (==3.0.0) ; extra == 'dev'
Requires-Dist: pytest-freezegun (==0.4.2) ; extra == 'dev'
Requires-Dist: pytest-mock (==3.7.0) ; extra == 'dev'
Requires-Dist: signxml (==2.9.0) ; extra == 'dev'
Requires-Dist: tox ; extra == 'dev'
Requires-Dist: wheel (==0.37.1) ; extra == 'dev'
Provides-Extra: django
Requires-Dist: django (<4.1,>=3.2) ; extra == 'django'
Requires-Dist: social-auth-app-django ; extra == 'django'
Provides-Extra: django-dev
Requires-Dist: pytest-django ; extra == 'django-dev'
